README.md
setup.py
src/perf_core/__init__.py
src/perf_core.egg-info/PKG-INFO
src/perf_core.egg-info/SOURCES.txt
src/perf_core.egg-info/dependency_links.txt
src/perf_core.egg-info/requires.txt
src/perf_core.egg-info/top_level.txt
src/perf_core/aws_utils/__init__.py
src/perf_core/aws_utils/cognito.py
src/perf_core/aws_utils/s3.py
src/perf_core/conf/__init__.py
src/perf_core/conf/commonconf.py
src/perf_core/database_utils/__init__.py
src/perf_core/database_utils/mysql.py
src/perf_core/fileUtils/__init__.py
src/perf_core/fileUtils/file_utils.py
src/perf_core/fileUtils/jira_utils.py
src/perf_core/google/__init__.py
src/perf_core/google/auth.py
src/perf_core/google/gmail_utils.py
src/perf_core/google/sheets_utils.py
src/perf_core/locust_utils/__init__.py
src/perf_core/locust_utils/locust_utils.py